haipy/haipy.py
haipy/data/prototypes.json
haipy-1.5.1.dist-info/LICENSE
haipy-1.5.1.dist-info/METADATA
haipy-1.5.1.dist-info/WHEEL
haipy-1.5.1.dist-info/entry_points.txt
haipy-1.5.1.dist-info/top_level.txt
haipy-1.5.1.dist-info/RECORD
