Metadata-Version: 2.1
Name: haipy
Version: 1.5.1
Summary: Hash Identifier for Python (derived from haiti)
Home-page: https://github.com/gcarmix/haipy
Download-URL: https://github.com/gcarmix/haipy/archive/master.zip
Author: gcarmix
Author-email: gcarmix <carmixdev@gmail.com>
Maintainer: gcarmix
Maintainer-email: carmixdev@gmail.com
License: MIT
Project-URL: Homepage, https://github.com/gcarmix/haipy
Project-URL: Bug Tracker, https://github.com/gcarmix/haipy/issues
Platform: LINUX
Platform: MAC
Platform: WINDOWS
Classifier: Programming Language :: Python :: 3
Classifier: License :: OSI Approved :: MIT License
Classifier: Operating System :: OS Independent
Requires-Python: >=3.7
License-File: LICENSE
Requires-Dist: importlib-resources
